duet/__init__.py
duet/_version.py
duet/aitertools.py
duet/duet_test.py
duet/futuretools.py
duet/futuretools_test.py
duet/impl.py
duet/impl_test.py
duet/py.typed
duet/typing.py
duet_async-0.1.3.dist-info/LICENSE
duet_async-0.1.3.dist-info/METADATA
duet_async-0.1.3.dist-info/WHEEL
duet_async-0.1.3.dist-info/top_level.txt
duet_async-0.1.3.dist-info/RECORD
