Metadata-Version: 2.1
Name: duet-async
Version: 0.1.3
Summary: A simple future-based async library for python.
Home-page: http://github.com/google/duet
Author: The Duet Authors
Author-email: maffoo@google.com
License: Apache 2
Platform: UNKNOWN
Requires-Python: >=3.7.0
Provides-Extra: dev_env
Requires-Dist: black (==20.8b1) ; extra == 'dev_env'
Requires-Dist: isort (==5.7.*) ; extra == 'dev_env'
Requires-Dist: mypy (==0.782.*) ; extra == 'dev_env'
Requires-Dist: pylint (==2.6.*) ; extra == 'dev_env'
Requires-Dist: pytest (==5.4.*) ; extra == 'dev_env'
Requires-Dist: twine (==3.3.*) ; extra == 'dev_env'
